{
  "username": "maccosmetics",
  "timestamp": "2025-05-09T21:08:08.254Z",
  "notification": {
    "type": "message",
    "sender_id": "539180445642894",
    "message_id": "aWdfZAG1faXRlbToxOklHTWVzc2FnZAUlEOjE3ODQxNDcxNzg2MjY5MzI1OjM0MDI4MjM2Njg0MTcxMDMwMTI0NDI3NjAxNzgyNzg1ODU2MDMyODozMjIyMzIzMDkxNzM3NTk1MDkwNDgxNjk3OTg5NzQ4MzI2NAZDZD",
    "text": "hey what is refunding policy of the maccosmetics?",
    "timestamp": 1746824884033,
    "received_at": "2025-05-09T21:08:04.033Z",
    "status": "pending"
  },
  "reply": "Hey! For questions about our refund policy, please check out the FAQ section on our website! You can find the link in our bio.",
  "mode": "instant"
}