{
  "username": "maccosmetics",
  "timestamp": "2025-05-09T20:28:46.416Z",
  "notification": {
    "type": "message",
    "instagram_user_id": "123456789",
    "sender_id": "987654321",
    "message_id": "test_message_123",
    "text": "Hi, do you have this lipstick in red?",
    "timestamp": 1746822502614,
    "received_at": "2025-05-09T20:28:22.614Z",
    "status": "pending"
  },
  "reply": "Hey there! We have tons of red lipsticks! Check out our website to find your perfect shade: m.maccosmetics.com ✨💄\n",
  "mode": "instant"
}